typedresult/__init__.py
typedresult/result.py
typed_result-0.0.0.dist-info/LICENSE
typed_result-0.0.0.dist-info/METADATA
typed_result-0.0.0.dist-info/WHEEL
typed_result-0.0.0.dist-info/top_level.txt
typed_result-0.0.0.dist-info/RECORD
